{"metadata":{"candidates":["HULL David","MURRAY Alan","CUTCHER Ned","FAKER John"],"contest":"2021 NSW Local Government election for Burwood Mayoral."},"solution":{"Ok":{"assertions":[{"assertion":{"type":"NEB","winner":3,"loser":1},"margin":8306,"difficulty":2.1426679508788826},{"assertion":{"type":"NEB","winner":3,"loser":2},"margin":7598,"difficulty":2.342326928138984},{"assertion":{"type":"NEN","winner":3,"loser":0,"continuing":[0,3]},"margin":7043,"difficulty":2.5269061479483175}],"difficulty":2.5269061479483175,"margin":7043,"winner":3,"num_candidates":4,"time_to_determine_winners":{"work":4,"seconds":5.69e-6},"time_to_find_assertions":{"work":5,"seconds":0.000034001},"time_to_trim_assertions":{"work":12,"seconds":1.659999999999996e-6}}}}